{
    "Keys" : [],
    "ID" : "5",
    "ModelName": "Модель Жакоба-Монода",
    "Expressions": 2,
    "Description" : "Опис моделі Жакоба-Монода",
    "Data": {
        "InputAttributes" : [
            "Популяція",
            "Концентрация речовин"
        ],
        "Coefs": [
            {
                "Name" : "Швидкість поглинання",
                "Tip" : "Коеф 1",
                "Value" : "0.6",
                "Letter" : "V"
            },
            {
                "Name" : "Постійна насичення",
                "Tip" : "Коеф 2",
                "Value" : "3",
                "Letter" : "K"
            },
            {
                "Name" : "Прибутковість для поп. від речовин",
                "Tip" : "Коэф 3",
                "Value" : "1",
                "Letter" : "Y"
            }
        ],
        "RoleNames" : [
            "Популяція",
            "Концентрация речовин"
        ]
    }
}
